two_point_interpolation/__init__.py
two_point_interpolation/constant_acc.py
two_point_interpolation/constant_jerk.py
two_point_interpolation/py.typed
two_point_interpolation-1.3.1.dist-info/LICENSE
two_point_interpolation-1.3.1.dist-info/METADATA
two_point_interpolation-1.3.1.dist-info/WHEEL
two_point_interpolation-1.3.1.dist-info/top_level.txt
two_point_interpolation-1.3.1.dist-info/RECORD
