Metadata-Version: 2.1
Name: two-point-interpolation
Version: 1.3.1
Summary: Two-point interpolation with constant acceleration and constant jerk
Author-email: Yuki Okamoto <yuokamoto1988@gmail.com>
License: Apache License
Project-URL: Homepage, https://github.com/yuokamoto/two_points_interpolation_py
Project-URL: Repository, https://github.com/yuokamoto/two_points_interpolation_py
Project-URL: Documentation, https://github.com/yuokamoto/two_points_interpolation_py#readme
Project-URL: Issues, https://github.com/yuokamoto/two_points_interpolation_py/issues
Keywords: robotics,trajectory,motion-planning,interpolation,acceleration,jerk
Classifier: Development Status :: 4 - Beta
Classifier: Intended Audience :: Developers
Classifier: Intended Audience :: Science/Research
Classifier: License :: OSI Approved :: Apache Software License
Classifier: Programming Language :: Python :: 3
Classifier: Programming Language :: Python :: 3.7
Classifier: Programming Language :: Python :: 3.8
Classifier: Programming Language :: Python :: 3.9
Classifier: Programming Language :: Python :: 3.10
Classifier: Programming Language :: Python :: 3.11
Classifier: Topic :: Scientific/Engineering
Classifier: Topic :: Scientific/Engineering :: Physics
Classifier: Topic :: Software Development :: Libraries :: Python Modules
Requires-Python: >=3.7
License-File: LICENSE
Requires-Dist: numpy>=1.19.0
Provides-Extra: dev
Requires-Dist: pytest>=7.0.0; extra == "dev"
Requires-Dist: pytest-cov>=4.0.0; extra == "dev"
Requires-Dist: matplotlib>=3.3.0; extra == "dev"
Requires-Dist: mypy>=1.0.0; extra == "dev"
Requires-Dist: pylint>=2.15.0; extra == "dev"
Requires-Dist: flake8>=5.0.0; extra == "dev"
Requires-Dist: autopep8>=2.0.0; extra == "dev"
Requires-Dist: pre-commit>=3.0.0; extra == "dev"
Provides-Extra: examples
Requires-Dist: matplotlib>=3.3.0; extra == "examples"
